userutils/__init__.py
userutils/examples.py
userutils/main.py
userutils/menu.py
userutils-2.0.0.dist-info/LICENSE
userutils-2.0.0.dist-info/METADATA
userutils-2.0.0.dist-info/WHEEL
userutils-2.0.0.dist-info/top_level.txt
userutils-2.0.0.dist-info/RECORD
