Metadata-Version: 2.1
Name: userutils
Version: 2.0.0
Summary: Makes working with humans easier
Home-page: https://github.com/Scoder12/userutils
Author: Scoder12
Author-email: realscoder12@gmail.com
License: MIT
Platform: UNKNOWN
Classifier: Programming Language :: Python :: 3
Classifier: License :: OSI Approved :: MIT License
Classifier: Operating System :: OS Independent
